xctph/__init__.py
xctph/elph.py
xctph/kpoints.py
xctph/units.py
xctph/xct.py
xctph/xctph.py
xctph/old_files/__init__.py
xctph/old_files/compute_xctph.py
xctph/old_files/print_eph.py
xctph/old_files/print_xctph.py
xctph/old_files/symmetrize_mtxel.py
xctph/old_files/write_eph_h5.py
xctph/old_files/write_xct_h5.py
xctph/utils/__init__.py
xctph/utils/k_plus_q.py
xctph/utils/logging.py
xctph-1.2.0.dist-info/METADATA
xctph-1.2.0.dist-info/WHEEL
xctph-1.2.0.dist-info/top_level.txt
xctph-1.2.0.dist-info/RECORD
