Metadata-Version: 2.4
Name: xctph
Version: 1.2.0
Summary: Package for computing exciton phonon matrix elements.
Author: Krishnaa Vadivel
Author-email: krishnaa.vadivel@yale.edu
Requires-Dist: numpy
Requires-Dist: scipy
Requires-Dist: mpi4py
Requires-Dist: h5py
Requires-Dist: ase
Requires-Dist: xmltodict
Requires-Dist: setuptools
Requires-Dist: jmespath
Dynamic: author
Dynamic: author-email
Dynamic: description
Dynamic: requires-dist
Dynamic: summary
